{
  "policies": [
    {
      "meta": {
        "version": "0.6",
        "policyId": "getRootPage",
        "description": "Retrieve the root page open to anyone"
      },
      "actions": [
        "http:GET:/"
      ],
      "subjects": [
        "any",
        "anyauthenticated"
      ],
      "object": "hexaIndustries"
    },
    {
      "meta": {
        "version": "0.6",
        "policyId": "getSales"
      },
      "actions": [
        "sales"
      ],
      "subjects": [
        "anyauthenticated",
        "sales@hexaindustries.io",
        "marketing@hexaindustries.io"
      ],
      "object": "hexaIndustries"
    },
    {
      "meta": {
        "version": "0.6",
        "policyId": "getAccounting"
      },
      "actions": [
        "http:GET:/accounting",
        "http:POST:/accounting"
      ],
      "subjects": [
        "accounting@hexaindustries.io"
      ],
      "object": "hexaIndustries"
    },
    {
      "meta": {
        "version": "0.6",
        "policyId": "getHumanResources"
      },
      "actions": [
        "http:GET:/humanresources"
      ],
      "subjects": [
        "humanresources@hexaindustries.io"
      ],
      "object": "hexaIndustries"
    }
  ]
}